{
  "bootstrapServers": "localhost:9092",
  "groupId": "notification-service-group",

  "TweetEventsName": "tweet-event",
  "UserEventsName": "user-event",

  "tweetEvents": {
    "tweetCreatedEventName": "tweet-created",
    "retweetEventName": "retweet-created",
    "replyEventName": "reply-created",
    "tweetDeletedEventName": "tweet-deleted",
    "likeSetEventName": "like-set",
    "likeCanceledEventName": "like-canceled"
  },

  "userEvents": {
    "profileChangedEventName": "profile-changed",
    "profileDeletedEventName": "profile-deleted",
    "userFollowedEventName": "user-followed",
    "userUnfollowedEventName": "user-unfollowed",
    "userBlockedEventName": "user-blocked"
  }
}
